maxprogress.py
maxprogress-0.4.2.dist-info/WHEEL
maxprogress-0.4.2.dist-info/METADATA
maxprogress-0.4.2.dist-info/RECORD
