Metadata-Version: 2.1
Name: maxprogress
Version: 0.4.2
Summary: A customized Rich Progress Bar.
License: MIT
Author-email: maxludden <dev@maxludden.com>
Requires-Python: >=3.10
Requires-Dist: maxconsole>=0.5.1
Requires-Dist: rich>=12.6.0
